{ "apricots_acres_area_bearing_national": {"data":[{"source_desc":"CENSUS","sector_desc":"CROPS","group_desc":"FRUIT & TREE NUTS","commodity_desc":"APRICOTS","class_desc":"ALL CLASSES","prodn_practice_desc":"ALL PRODUCTION PRACTICES","util_practice_desc":"ALL UTILIZATION PRACTICES","statisticcat_desc":"AREA BEARING","unit_desc":"ACRES","domain_desc":"TOTAL","domaincat_desc":"NOT SPECIFIED","data_item":"APRICOTS,ALL UTILIZATION PRACTICES,ALL PRODUCTION PRACTICES,ALL CLASSES,ACRES,AREA BEARING","agg_level_desc":"NATIONAL","state_ansi":"","state_fips_code":"99","state_alpha":"US","state_name":"US TOTAL","asd_code":null,"asd_desc":null,"county_ansi":null,"county_code":null,"county_name":null,"region_desc":"","zip_5":"","watershed_code":"00000000","watershed_desc":"","congr_district_code":"","country_code":"9000","country_name":"UNITED STATES","location_desc":"US TOTAL","year":"2012","freq_desc":"ANNUAL","begin_code":"00","end_code":"00","reference_period_desc":"YEAR","week_ending":"","load_time":"2012-12-31 00:00:00","value":"11,286","CV":"7.9"}]}}